{
 "creation": "2021-08-31 16:52:47.085046",
 "doctype": "DocType",
 "document_type": "Document",
 "editable_grid": 1,
 "engine": "InnoDB",
 "field_order": [
  "barcode",
  "item_code",
  "item_name",
  "col_break1",
  "customer_item_code",
  "section_break_6",
  "description",
  "brand",
  "item_group",
  "image_section",
  "image",
  "image_view",
  "quantity_and_rate",
  "qty",
  "stock_uom",
  "col_break2",
  "uom",
  "conversion_factor",
  "stock_qty",
  "item_weight_details",
  "weight_per_unit",
  "total_weight",
  "column_break_21",
  "weight_uom",
  "warehouse_and_reference",
  "warehouse",
  "target_warehouse",
  "quality_inspection",
  "col_break4",
  "against_sales_order",
  "so_detail",
  "against_sales_invoice",
  "si_detail",
  "ssr_detail",
  "dn_detail",
  "section_break_40",
  "batch_no",
  "note",
  "serial_no",
  "actual_batch_qty",
  "actual_qty",
  "accounting_details_section",
  "return_account",
  "expense_account",
  "allow_zero_valuation_rate",
  "column_break_71",
  "accounting_dimensions_section",
  "cost_center",
  "dimension_col_break",
  "project",
  "reason_for_return_section_break",
  "reason_for_return",
  "section_break_72",
  "page_break"
 ],
 "fields": [
  {
   "fieldname": "barcode",
   "fieldtype": "Data",
   "label": "Barcode",
   "print_hide": 1
  },
  {
   "columns": 6,
   "fieldname": "item_code",
   "fieldtype": "Link",
   "in_global_search": 1,
   "in_list_view": 1,
   "label": "Item Code",
   "oldfieldname": "item_code",
   "oldfieldtype": "Link",
   "options": "Item",
   "print_width": "150px",
   "reqd": 1,
   "search_index": 1,
   "width": "150px"
  },
  {
   "fieldname": "item_name",
   "fieldtype": "Data",
   "in_global_search": 1,
   "label": "Item Name",
   "oldfieldname": "item_name",
   "oldfieldtype": "Data",
   "print_hide": 1,
   "print_width": "150px",
   "reqd": 1,
   "width": "150px"
  },
  {
   "fieldname": "col_break1",
   "fieldtype": "Column Break"
  },
  {
   "fieldname": "customer_item_code",
   "fieldtype": "Data",
   "hidden": 1,
   "label": "Customer's Item Code",
   "print_hide": 1,
   "read_only": 1
  },
  {
   "collapsible": 1,
   "fieldname": "section_break_6",
   "fieldtype": "Section Break",
   "label": "Description"
  },
  {
   "fieldname": "description",
   "fieldtype": "Text Editor",
   "label": "Description",
   "oldfieldname": "description",
   "oldfieldtype": "Small Text",
   "print_width": "300px",
   "reqd": 1,
   "width": "300px"
  },
  {
   "fieldname": "brand",
   "fieldtype": "Link",
   "hidden": 1,
   "label": "Brand Name",
   "oldfieldname": "brand",
   "oldfieldtype": "Link",
   "options": "Brand",
   "print_hide": 1,
   "print_width": "150px",
   "read_only": 1,
   "width": "150px"
  },
  {
   "fieldname": "item_group",
   "fieldtype": "Link",
   "hidden": 1,
   "label": "Item Group",
   "oldfieldname": "item_group",
   "oldfieldtype": "Link",
   "options": "Item Group",
   "print_hide": 1,
   "read_only": 1
  },
  {
   "collapsible": 1,
   "fieldname": "image_section",
   "fieldtype": "Section Break",
   "label": "Image"
  },
  {
   "fieldname": "image",
   "fieldtype": "Attach",
   "hidden": 1,
   "label": "Image"
  },
  {
   "fieldname": "image_view",
   "fieldtype": "Image",
   "label": "Image View",
   "options": "image",
   "print_hide": 1
  },
  {
   "fieldname": "quantity_and_rate",
   "fieldtype": "Section Break",
   "label": "Quantity and Rate"
  },
  {
   "columns": 1,
   "fieldname": "qty",
   "fieldtype": "Float",
   "in_list_view": 1,
   "label": "Quantity",
   "oldfieldname": "qty",
   "oldfieldtype": "Currency",
   "print_width": "100px",
   "reqd": 1,
   "width": "50px"
  },
  {
   "fieldname": "stock_uom",
   "fieldtype": "Link",
   "label": "Stock UOM",
   "oldfieldname": "stock_uom",
   "oldfieldtype": "Data",
   "options": "UOM",
   "print_hide": 1,
   "print_width": "50px",
   "read_only": 1,
   "reqd": 1,
   "width": "50px"
  },
  {
   "fieldname": "col_break2",
   "fieldtype": "Column Break"
  },
  {
   "columns": 1,
   "fieldname": "uom",
   "fieldtype": "Link",
   "in_list_view": 1,
   "label": "UOM",
   "options": "UOM",
   "reqd": 1
  },
  {
   "fieldname": "conversion_factor",
   "fieldtype": "Float",
   "label": "UOM Conversion Factor",
   "print_hide": 1,
   "read_only": 1,
   "reqd": 1
  },
  {
   "fieldname": "stock_qty",
   "fieldtype": "Float",
   "label": "Qty as per Stock UOM",
   "no_copy": 1,
   "print_hide": 1,
   "read_only": 1
  },
  {
   "collapsible": 1,
   "fieldname": "item_weight_details",
   "fieldtype": "Section Break",
   "label": "Item Weight Details"
  },
  {
   "fieldname": "weight_per_unit",
   "fieldtype": "Float",
   "label": "Weight Per Unit"
  },
  {
   "fieldname": "total_weight",
   "fieldtype": "Float",
   "label": "Total Weight",
   "read_only": 1
  },
  {
   "fieldname": "column_break_21",
   "fieldtype": "Column Break",
   "print_hide": 1
  },
  {
   "fieldname": "weight_uom",
   "fieldtype": "Link",
   "label": "Weight UOM",
   "options": "UOM"
  },
  {
   "fieldname": "warehouse_and_reference",
   "fieldtype": "Section Break",
   "label": "Warehouse and Reference"
  },
  {
   "depends_on": "eval:!doc.__islocal",
   "fieldname": "quality_inspection",
   "fieldtype": "Link",
   "label": "Quality Inspection",
   "no_copy": 1,
   "options": "Quality Inspection",
   "print_hide": 1
  },
  {
   "fieldname": "col_break4",
   "fieldtype": "Column Break"
  },
  {
   "fieldname": "against_sales_order",
   "fieldtype": "Link",
   "label": "Against Sales Order",
   "no_copy": 1,
   "options": "Sales Order",
   "print_hide": 1,
   "read_only": 1
  },
  {
   "fieldname": "so_detail",
   "fieldtype": "Data",
   "hidden": 1,
   "label": "Against Sales Order Item",
   "no_copy": 1,
   "oldfieldname": "prevdoc_detail_docname",
   "oldfieldtype": "Data",
   "print_hide": 1,
   "print_width": "150px",
   "read_only": 1,
   "search_index": 1,
   "width": "150px"
  },
  {
   "fieldname": "against_sales_invoice",
   "fieldtype": "Link",
   "label": "Against Sales Invoice",
   "no_copy": 1,
   "options": "Sales Invoice",
   "print_hide": 1,
   "read_only": 1
  },
  {
   "fieldname": "si_detail",
   "fieldtype": "Data",
   "hidden": 1,
   "label": "Against Sales Invoice Item",
   "no_copy": 1,
   "print_hide": 1,
   "read_only": 1
  },
  {
   "fieldname": "dn_detail",
   "fieldtype": "Data",
   "hidden": 1,
   "label": "Against Delivery Note Item",
   "no_copy": 1,
   "print_hide": 1,
   "read_only": 1
  },
  {
   "fieldname": "section_break_40",
   "fieldtype": "Section Break"
  },
  {
   "columns": 2,
   "fieldname": "batch_no",
   "fieldtype": "Link",
   "in_list_view": 1,
   "label": "Batch No",
   "oldfieldname": "batch_no",
   "oldfieldtype": "Link",
   "options": "Batch",
   "print_hide": 1
  },
  {
   "fieldname": "serial_no",
   "fieldtype": "Text",
   "in_list_view": 1,
   "label": "Serial No",
   "no_copy": 1,
   "oldfieldname": "serial_no",
   "oldfieldtype": "Text"
  },
  {
   "allow_on_submit": 1,
   "depends_on": "batch_no",
   "fieldname": "actual_batch_qty",
   "fieldtype": "Float",
   "label": "Available Batch Qty at From Warehouse",
   "no_copy": 1,
   "print_hide": 1,
   "print_width": "150px",
   "read_only": 1,
   "width": "150px"
  },
  {
   "allow_on_submit": 1,
   "fieldname": "actual_qty",
   "fieldtype": "Float",
   "label": "Available Qty at From Warehouse",
   "no_copy": 1,
   "oldfieldname": "actual_qty",
   "oldfieldtype": "Currency",
   "print_hide": 1,
   "print_width": "150px",
   "read_only": 1,
   "width": "150px"
  },
  {
   "fieldname": "accounting_details_section",
   "fieldtype": "Section Break",
   "label": "Accounting Details"
  },
  {
   "fieldname": "expense_account",
   "fieldtype": "Link",
   "label": "Expense Account",
   "no_copy": 1,
   "options": "Account",
   "print_hide": 1,
   "width": "120px"
  },
  {
   "default": "0",
   "fieldname": "allow_zero_valuation_rate",
   "fieldtype": "Check",
   "label": "Allow Zero Valuation Rate",
   "no_copy": 1,
   "print_hide": 1
  },
  {
   "fieldname": "column_break_71",
   "fieldtype": "Column Break"
  },
  {
   "collapsible": 1,
   "fieldname": "accounting_dimensions_section",
   "fieldtype": "Section Break",
   "label": "Accounting Dimensions"
  },
  {
   "default": ":Company",
   "fieldname": "cost_center",
   "fieldtype": "Link",
   "label": "Cost Center",
   "no_copy": 1,
   "options": "Cost Center",
   "print_hide": 1,
   "width": "120px"
  },
  {
   "fieldname": "dimension_col_break",
   "fieldtype": "Column Break"
  },
  {
   "fieldname": "project",
   "fieldtype": "Link",
   "label": "Project",
   "options": "Project"
  },
  {
   "default": "0",
   "depends_on": "eval:parent.is_return==1",
   "fieldname": "reason_for_return_section_break",
   "fieldtype": "Section Break",
   "label": "Reason For Return"
  },
  {
   "fieldname": "reason_for_return",
   "fieldtype": "Small Text",
   "label": "Reason for Return",
   "no_copy": 1
  },
  {
   "fieldname": "section_break_72",
   "fieldtype": "Section Break"
  },
  {
   "allow_on_submit": 1,
   "default": "0",
   "fieldname": "page_break",
   "fieldtype": "Check",
   "label": "Page Break",
   "oldfieldname": "page_break",
   "oldfieldtype": "Check",
   "print_hide": 1
  },
  {
   "fieldname": "target_warehouse",
   "fieldtype": "Link",
   "hidden": 1,
   "ignore_user_permissions": 1,
   "label": "Customer Warehouse (Optional)",
   "no_copy": 1,
   "options": "Warehouse",
   "print_hide": 1
  },
  {
   "fieldname": "warehouse",
   "fieldtype": "Link",
   "label": "Warehouse",
   "oldfieldname": "warehouse",
   "oldfieldtype": "Link",
   "options": "Warehouse",
   "print_hide": 1,
   "print_width": "100px",
   "width": "100px"
  },
  {
   "fieldname": "ssr_detail",
   "fieldtype": "Data",
   "label": "Sales Stock Return"
  },
  {
   "fieldname": "note",
   "fieldtype": "Data",
   "label": "Note"
  },
  {
   "default": "41120.01 - Retur Penjualan - QL",
   "fieldname": "return_account",
   "fieldtype": "Link",
   "label": "Return Account",
   "options": "Account"
  }
 ],
 "istable": 1,
 "modified": "2021-09-01 17:44:58.881071",
 "modified_by": "Administrator",
 "module": "QL",
 "name": "Sales Stock Return Item",
 "owner": "Administrator",
 "permissions": [],
 "sort_field": "modified",
 "sort_order": "DESC"
}